aiohttp_security/__init__.py
aiohttp_security/abc.py
aiohttp_security/api.py
aiohttp_security/cookies_identity.py
aiohttp_security/jwt_identity.py
aiohttp_security/py.typed
aiohttp_security/session_identity.py
demo/__init__.py
demo/simple_example_auth.py
demo/database_auth/__init__.py
demo/database_auth/__main__.py
demo/database_auth/db.py
demo/database_auth/db_auth.py
demo/database_auth/handlers.py
demo/database_auth/main.py
demo/dictionary_auth/__init__.py
demo/dictionary_auth/authz.py
demo/dictionary_auth/handlers.py
demo/dictionary_auth/main.py
demo/dictionary_auth/users.py
tests/__init__.py
tests/conftest.py
tests/test_cookies_identity.py
tests/test_dict_autz.py
tests/test_jwt_identity.py
tests/test_no_auth.py
tests/test_no_identity.py
tests/test_session_identity.py
aiohttp_security-0.5.0.dist-info/LICENSE
aiohttp_security-0.5.0.dist-info/METADATA
aiohttp_security-0.5.0.dist-info/WHEEL
aiohttp_security-0.5.0.dist-info/top_level.txt
aiohttp_security-0.5.0.dist-info/RECORD
