Metadata-Version: 2.1
Name: aiohttp-security
Version: 0.5.0
Summary: security for aiohttp.web
Home-page: https://github.com/aio-libs/aiohttp_security/
Author: Andrew Svetlov
Author-email: andrew.svetlov@gmail.com
License: Apache 2
Classifier: License :: OSI Approved :: Apache Software License
Classifier: Intended Audience :: Developers
Classifier: Programming Language :: Python
Classifier: Programming Language :: Python :: 3
Classifier: Programming Language :: Python :: 3.8
Classifier: Programming Language :: Python :: 3.9
Classifier: Programming Language :: Python :: 3.10
Classifier: Programming Language :: Python :: 3.11
Classifier: Programming Language :: Python :: 3.12
Classifier: Topic :: Internet :: WWW/HTTP
Classifier: Framework :: AsyncIO
License-File: LICENSE
Requires-Dist: aiohttp >=3.9
Provides-Extra: session
Requires-Dist: aiohttp-session ; extra == 'session'
